README.rst
setup.cfg
setup.py
pyramid_health/__init__.py
pyramid_health/tests.py
pyramid_health.egg-info/PKG-INFO
pyramid_health.egg-info/SOURCES.txt
pyramid_health.egg-info/dependency_links.txt
pyramid_health.egg-info/pbr.json
pyramid_health.egg-info/requires.txt
pyramid_health.egg-info/top_level.txt