Metadata-Version: 1.0
Name: pyramid-health
Version: 1.2.1
Summary: Healthcheck extension for Pyramid
Home-page: https://github.com/ludia/pyramid_health
Author: Pior Bastida
Author-email: pbastida@ludia.com
License: UNKNOWN
Platform: UNKNOWN
